dictionary/__init__.py
dictionary/dictionary.py
berkeceranPyPI-2.0.0.dist-info/METADATA
berkeceranPyPI-2.0.0.dist-info/WHEEL
berkeceranPyPI-2.0.0.dist-info/top_level.txt
berkeceranPyPI-2.0.0.dist-info/RECORD
