Metadata-Version: 2.1
Name: berkeceranPyPI
Version: 2.0.0
Summary: UNKNOWN
Author: Berke Ceran
License: UNKNOWN
Platform: UNKNOWN
Requires-Python: >=3.8
Requires-Dist: requests (>=2.23.0)
